{
  "id": 6,
  "name": "Women's Running Leggings",
  "slug": "womens-running-leggings",
  "description": "High-waist compression leggings with phone pocket.",
  "price": 39.99,
  "original_price": null,
  "stock": 85,
  "category_id": 2,
  "image_url": "https://images.unsplash.com/photo-1506629082955-511b1aa562c8?w=400&h=300&fit=crop",
  "sku": "CLTH-002",
  "is_featured": false,
  "created_at": "2026-01-06T00:00:00",
  "category": {
    "id": 2,
    "name": "Clothing",
    "slug": "clothing",
    "description": ""
  },
  "reviews": [],
  "rating_avg": 0.0,
  "rating_count": 0,
  "rating_distribution": {
    "1": 0,
    "2": 0,
    "3": 0,
    "4": 0,
    "5": 0
  }
}